semantic_frame/__init__.py
semantic_frame/main.py
semantic_frame/py.typed
semantic_frame/core/__init__.py
semantic_frame/core/analyzers.py
semantic_frame/core/correlations.py
semantic_frame/core/enums.py
semantic_frame/core/translator.py
semantic_frame/integrations/__init__.py
semantic_frame/integrations/anthropic.py
semantic_frame/integrations/crewai.py
semantic_frame/integrations/langchain.py
semantic_frame/integrations/mcp.py
semantic_frame/integrations/mcp_wrapper.py
semantic_frame/interfaces/__init__.py
semantic_frame/interfaces/json_schema.py
semantic_frame/interfaces/llm_templates.py
semantic_frame/narrators/__init__.py
semantic_frame/narrators/correlation.py
semantic_frame/narrators/distribution.py
semantic_frame/narrators/time_series.py
semantic_frame/trading/__init__.py
semantic_frame/trading/allocation.py
semantic_frame/trading/anomalies.py
semantic_frame/trading/drawdown.py
semantic_frame/trading/enums.py
semantic_frame/trading/metrics.py
semantic_frame/trading/rankings.py
semantic_frame/trading/regime.py
semantic_frame/trading/schemas.py
semantic_frame/trading/windows.py
semantic_frame-0.4.0.dist-info/METADATA
semantic_frame-0.4.0.dist-info/WHEEL
semantic_frame-0.4.0.dist-info/licenses/LICENSE
semantic_frame-0.4.0.dist-info/RECORD
