Metadata-Version: 2.4
Name: semantic-frame
Version: 0.4.0
Summary: Semantic compression layer for numerical data - token-efficient LLM context with Anthropic Advanced Tool Use support
Project-URL: Homepage, https://github.com/Anarkitty1/semantic-frame
Project-URL: Repository, https://github.com/Anarkitty1/semantic-frame
Project-URL: Documentation, https://github.com/Anarkitty1/semantic-frame#readme
Project-URL: Changelog, https://github.com/Anarkitty1/semantic-frame/blob/main/CHANGELOG.md
Author-email: Anarkitty1 <emma@example.com>
License-Expression: MIT
License-File: LICENSE
Keywords: ai-agents,anthropic,backtesting,crewai,data-compression,drawdown,langchain,llm,mcp,numpy,pandas,polars,semantic,tool-use,trading
Classifier: Development Status :: 4 - Beta
Classifier: Intended Audience :: Developers
Classifier: License :: OSI Approved :: MIT License
Classifier: Programming Language :: Python :: 3
Classifier: Programming Language :: Python :: 3.10
Classifier: Programming Language :: Python :: 3.11
Classifier: Programming Language :: Python :: 3.12
Classifier: Topic :: Scientific/Engineering :: Artificial Intelligence
Classifier: Topic :: Software Development :: Libraries :: Python Modules
Classifier: Typing :: Typed
Requires-Python: >=3.10
Requires-Dist: numpy>=1.20
Requires-Dist: pandas>=1.3
Requires-Dist: polars>=0.20
Requires-Dist: pydantic>=2.0
Requires-Dist: scipy>=1.9
Provides-Extra: all
Requires-Dist: anthropic>=0.20; extra == 'all'
Requires-Dist: crewai>=0.1; extra == 'all'
Requires-Dist: langchain>=0.1; extra == 'all'
Requires-Dist: matplotlib>=3.5; extra == 'all'
Requires-Dist: mcp>=1.0.0; extra == 'all'
Requires-Dist: plotly>=5.0; extra == 'all'
Requires-Dist: tiktoken>=0.5.0; extra == 'all'
Provides-Extra: anthropic
Requires-Dist: anthropic>=0.20; extra == 'anthropic'
Provides-Extra: benchmarks
Requires-Dist: anthropic>=0.20; extra == 'benchmarks'
Requires-Dist: matplotlib>=3.5; extra == 'benchmarks'
Requires-Dist: plotly>=5.0; extra == 'benchmarks'
Provides-Extra: crewai
Requires-Dist: crewai>=0.1; extra == 'crewai'
Provides-Extra: dev
Requires-Dist: mypy>=1.0; extra == 'dev'
Requires-Dist: pytest-cov>=4.0; extra == 'dev'
Requires-Dist: pytest>=7.0; extra == 'dev'
Requires-Dist: ruff>=0.1; extra == 'dev'
Provides-Extra: langchain
Requires-Dist: langchain>=0.1; extra == 'langchain'
Provides-Extra: mcp
Requires-Dist: mcp[cli]>=1.0.0; extra == 'mcp'
Provides-Extra: validation
Requires-Dist: tiktoken>=0.5.0; extra == 'validation'
Provides-Extra: viz
Requires-Dist: matplotlib>=3.5; extra == 'viz'
Requires-Dist: plotly>=5.0; extra == 'viz'
